WutongDeJiqiXuexiDiyiji/README.md
WutongDeJiqiXuexiDiyiji/__init__.py
WutongDeJiqiXuexiDiyiji/__main__.py
WutongDeJiqiXuexiDiyiji/file.epub
WutongDeJiqiXuexiDiyiji/index.html
WutongDeJiqiXuexiDiyiji/css/__init__.py
WutongDeJiqiXuexiDiyiji/css/annotations.css
WutongDeJiqiXuexiDiyiji/css/main.css
WutongDeJiqiXuexiDiyiji/css/normalize.css
WutongDeJiqiXuexiDiyiji/css/popup.css
WutongDeJiqiXuexiDiyiji/font/__init__.py
WutongDeJiqiXuexiDiyiji/font/fontello.eot
WutongDeJiqiXuexiDiyiji/font/fontello.svg
WutongDeJiqiXuexiDiyiji/font/fontello.ttf
WutongDeJiqiXuexiDiyiji/font/fontello.woff
WutongDeJiqiXuexiDiyiji/img/__init__.py
WutongDeJiqiXuexiDiyiji/img/annotator-glyph-sprite.png
WutongDeJiqiXuexiDiyiji/img/annotator-icon-sprite.png
WutongDeJiqiXuexiDiyiji/img/apple-touch-icon.png
WutongDeJiqiXuexiDiyiji/img/cancelfullscreen.png
WutongDeJiqiXuexiDiyiji/img/close.png
WutongDeJiqiXuexiDiyiji/img/fullscreen.png
WutongDeJiqiXuexiDiyiji/img/loader.gif
WutongDeJiqiXuexiDiyiji/img/menu-icon.png
WutongDeJiqiXuexiDiyiji/img/save.png
WutongDeJiqiXuexiDiyiji/img/saved.png
WutongDeJiqiXuexiDiyiji/img/settings-s.png
WutongDeJiqiXuexiDiyiji/img/settings.png
WutongDeJiqiXuexiDiyiji/img/star.png
WutongDeJiqiXuexiDiyiji/js/__init__.py
WutongDeJiqiXuexiDiyiji/js/epub.js
WutongDeJiqiXuexiDiyiji/js/epub.min.js
WutongDeJiqiXuexiDiyiji/js/epub.min.map
WutongDeJiqiXuexiDiyiji/js/hooks.min.js
WutongDeJiqiXuexiDiyiji/js/hooks.min.map
WutongDeJiqiXuexiDiyiji/js/reader.js
WutongDeJiqiXuexiDiyiji/js/reader.js.map
WutongDeJiqiXuexiDiyiji/js/reader.min.js
WutongDeJiqiXuexiDiyiji/js/reader.min.map
WutongDeJiqiXuexiDiyiji/js/hooks/__init__.py
WutongDeJiqiXuexiDiyiji/js/hooks/extensions/__init__.py
WutongDeJiqiXuexiDiyiji/js/hooks/extensions/highlight.js
WutongDeJiqiXuexiDiyiji/js/libs/__init__.py
WutongDeJiqiXuexiDiyiji/js/libs/jquery.min.js
WutongDeJiqiXuexiDiyiji/js/libs/localforage.min.js
WutongDeJiqiXuexiDiyiji/js/libs/screenfull.js
WutongDeJiqiXuexiDiyiji/js/libs/screenfull.min.js
wutong_de_jiqi_xuexi_diyiji-2024.3.2.0.dist-info/METADATA
wutong_de_jiqi_xuexi_diyiji-2024.3.2.0.dist-info/WHEEL
wutong_de_jiqi_xuexi_diyiji-2024.3.2.0.dist-info/entry_points.txt
wutong_de_jiqi_xuexi_diyiji-2024.3.2.0.dist-info/top_level.txt
wutong_de_jiqi_xuexi_diyiji-2024.3.2.0.dist-info/RECORD
